[
    {
        "type": "indicator",
        "spec_version": "2.1",
        "id": "indicator--158816f5-02ba-4539-b7fe-e1e955052f86",
        "created_by_ref": "identity--f8d34e5b-fbf0-451c-9fa3-d1312372bef5",
        "created": "2021-03-14T18:05:54.845764Z",
        "modified": "2021-08-14T01:08:33.948971Z",
        "description": "Include campaign six whether hot.",
        "indicator_types": [
            "unknown",
            "anonymization"
        ],
        "pattern": "[url:value > 'https://neal.com/'] FOLLOWEDBY [autonomous-system:rir >= 'Barry-Bailey'] START t'2021-06-08T18:07:26.72128Z' STOP t'2022-03-06T23:41:41.24719Z'",
        "pattern_type": "stix",
        "pattern_version": "2.1",
        "valid_from": "2022-03-21T00:06:08.650571Z",
        "valid_until": "2022-06-06T12:20:32.890322Z",
        "labels": [
            "pfte-batch-1"
        ],
        "confidence": 43,
        "lang": "en",
        "object_marking_refs": [
            "marking-definition--f88d31f6-486f-44da-b317-01333bde0b82"
        ]
    },
    {
        "type": "threat-actor",
        "spec_version": "2.1",
        "id": "threat-actor--50935d45-3d6c-481f-a904-9c487feb6234",
        "created_by_ref": "identity--f8d34e5b-fbf0-451c-9fa3-d1312372bef5",
        "created": "2021-08-03T17:06:10.245707Z",
        "modified": "2021-12-28T12:06:31.478905Z",
        "name": "learn",
        "aliases": [
            "live",
            "science"
        ],
        "last_seen": "2020-09-27T18:22:48.100028Z",
        "roles": [
            "malware-author"
        ],
        "primary_motivation": "coercion",
        "personal_motivations": [
            "organizational-gain",
            "notoriety",
            "revenge"
        ],
        "labels": [
            "minute",
            "plan",
            "school",
            "card",
            "say",
            "pfte-batch-1"
        ],
        "confidence": 42,
        "object_marking_refs": [
            "marking-definition--f88d31f6-486f-44da-b317-01333bde0b82"
        ]
    },
    {
        "type": "relationship",
        "spec_version": "2.1",
        "id": "relationship--6e555b9c-9532-44fb-a6d3-b142b709719f",
        "created_by_ref": "identity--f8d34e5b-fbf0-451c-9fa3-d1312372bef5",
        "created": "2021-04-04T09:39:18.45376Z",
        "modified": "2021-08-14T01:08:33.951422Z",
        "relationship_type": "indicates",
        "source_ref": "indicator--158816f5-02ba-4539-b7fe-e1e955052f86",
        "target_ref": "threat-actor--50935d45-3d6c-481f-a904-9c487feb6234",
        "stop_time": "2020-11-10T06:25:41.339275Z",
        "labels": [
            "front",
            "money",
            "half",
            "involve",
            "pfte-batch-1"
        ],
        "confidence": 33,
        "lang": "en",
        "external_references": [
            {
                "source_name": "study",
                "description": "Movie always woman theory.",
                "url": "https://moore-washington.com/",
                "hashes": {
                    "MD5": "02149fdc5949776bc6993ffa097b097c",
                    "SHA-1": "400d78ff2d1d388afe71aea38eff054f627a0017",
                    "SHA-256": "8679ed614e3b6360cede8a6086d153fd41679e6374cccf1e54916bcb9adf0080",
                    "SHA-512": "32e8ce0494b899b0258473c3f850358c1654f7ee630a15c811377fec2357b07979d58fb576f40a95c31be120cec66642bd869045c53a095b940be3655f4587b3",
                    "SHA3-256": "5a0caace01ab82453dde1b65de65937f2e442a14ebe721948555c9cb28ca6272",
                    "SHA3-512": "f767c80891e80d92b8856947da5164a3d686cc686304b2a5d611091feeac080b92e13cdd6e3b956a3dfaf3bb71e8c8aeb0493c8c7fb751f2bdaf9f4a2dbbe4f0"
                },
                "external_id": "XHfMs"
            },
            {
                "source_name": "door",
                "description": "Four away study others.",
                "url": "https://www.peterson.net/",
                "hashes": {
                    "MD5": "4c2e11ae80325c0565bdc78f5bb48370",
                    "SHA-1": "329a48ae2d86572edf2ca4089e73de2d27b61f3f",
                    "SHA-256": "f1264f2973509fc5aa8a14ee70f3cb7627cb178cc52404591e89db410436fb0a",
                    "SHA-512": "f962c1cf3ecccd090f7e8c5fedf7495aa73c1141a946eef9b38381e7cdd1ee41617cde0cf59aa86c40ef6eb74c604065d6e64b9a88194560c0cea063eab59f02",
                    "SHA3-256": "32cba596e7eb5d0330bb5fdd37e170fe47dafd84cf20e084f4d4a601ff95d4c4",
                    "SHA3-512": "279f014dbe81dea67e3688fc8e789b39e8a1a3afbf1fbb1a6292b469ac5884d325f6a431a63af66ddd74befb71a160312c113df707b3b801ece0ffebf0015f6d"
                }
            },
            {
                "source_name": "think",
                "description": "Evidence option candidate capital sing.",
                "url": "https://www.ramos.info/"
            },
            {
                "source_name": "could",
                "url": "http://barry.com/"
            }
        ],
        "object_marking_refs": [
            "marking-definition--f88d31f6-486f-44da-b317-01333bde0b82"
        ]
    },
    {
        "type": "identity",
        "spec_version": "2.1",
        "id": "identity--f8d34e5b-fbf0-451c-9fa3-d1312372bef5",
        "created_by_ref": "identity--b3bca3c2-1f3d-4b54-b44f-dac42c3a8f01",
        "created": "2020-01-01T00:00:00.000Z",
        "modified": "2020-01-01T00:00:00.000Z",
        "name": "USA.USG",
        "identity_class": "organization",
        "labels": [
            "ais-consent-everyone",
            "pfte-batch-1",
            "pfte-batch-1",
            "pfte-batch-1",
            "pfte-batch-1",
            "pfte-batch-1",
            "pfte-batch-1",
            "pfte-batch-1",
            "pfte-batch-1",
            "pfte-batch-1",
            "pfte-batch-1",
            "pfte-batch-1",
            "pfte-batch-1",
            "pfte-batch-1",
            "pfte-batch-1",
            "pfte-batch-1",
            "pfte-batch-1",
            "pfte-batch-1",
            "pfte-batch-1",
            "pfte-batch-1",
            "pfte-batch-1",
            "pfte-batch-1",
            "pfte-batch-1",
            "pfte-batch-1",
            "pfte-batch-1",
            "pfte-batch-1",
            "pfte-batch-1",
            "pfte-batch-1",
            "pfte-batch-1",
            "pfte-batch-1",
            "pfte-batch-1",
            "pfte-batch-1",
            "pfte-batch-1",
            "pfte-batch-1",
            "pfte-batch-1",
            "pfte-batch-1",
            "pfte-batch-1",
            "pfte-batch-1",
            "pfte-batch-1",
            "pfte-batch-1",
            "pfte-batch-1",
            "pfte-batch-1",
            "pfte-batch-1",
            "pfte-batch-1",
            "pfte-batch-1",
            "pfte-batch-1",
            "pfte-batch-1",
            "pfte-batch-1",
            "pfte-batch-1",
            "pfte-batch-1",
            "pfte-batch-1",
            "pfte-batch-1",
            "pfte-batch-1",
            "pfte-batch-1",
            "pfte-batch-1",
            "pfte-batch-1",
            "pfte-batch-1",
            "pfte-batch-1",
            "pfte-batch-1",
            "pfte-batch-1",
            "pfte-batch-1",
            "pfte-batch-1",
            "pfte-batch-1",
            "pfte-batch-1",
            "pfte-batch-1",
            "pfte-batch-1",
            "pfte-batch-1",
            "pfte-batch-1",
            "pfte-batch-1",
            "pfte-batch-1",
            "pfte-batch-1",
            "pfte-batch-1",
            "pfte-batch-1",
            "pfte-batch-1",
            "pfte-batch-1",
            "pfte-batch-1",
            "pfte-batch-1",
            "pfte-batch-1",
            "pfte-batch-1",
            "pfte-batch-1",
            "pfte-batch-1",
            "pfte-batch-1",
            "pfte-batch-1",
            "pfte-batch-1",
            "pfte-batch-1",
            "pfte-batch-1",
            "pfte-batch-1",
            "pfte-batch-1",
            "pfte-batch-1",
            "pfte-batch-1",
            "pfte-batch-1",
            "pfte-batch-1",
            "pfte-batch-1",
            "pfte-batch-1",
            "pfte-batch-1",
            "pfte-batch-1",
            "pfte-batch-1",
            "pfte-batch-1",
            "pfte-batch-1",
            "pfte-batch-1",
            "pfte-batch-1",
            "pfte-batch-1",
            "pfte-batch-1",
            "pfte-batch-1",
            "pfte-batch-1",
            "pfte-batch-1",
            "pfte-batch-1",
            "pfte-batch-1",
            "pfte-batch-1",
            "pfte-batch-1",
            "pfte-batch-1",
            "pfte-batch-1",
            "pfte-batch-1",
            "pfte-batch-1",
            "pfte-batch-1",
            "pfte-batch-1",
            "pfte-batch-1",
            "pfte-batch-1",
            "pfte-batch-1",
            "pfte-batch-1",
            "pfte-batch-1",
            "pfte-batch-1",
            "pfte-batch-1",
            "pfte-batch-1",
            "pfte-batch-1",
            "pfte-batch-1",
            "pfte-batch-1",
            "pfte-batch-1",
            "pfte-batch-1",
            "pfte-batch-1",
            "pfte-batch-1",
            "pfte-batch-1",
            "pfte-batch-1",
            "pfte-batch-1",
            "pfte-batch-1",
            "pfte-batch-1",
            "pfte-batch-1",
            "pfte-batch-1",
            "pfte-batch-1",
            "pfte-batch-1",
            "pfte-batch-1",
            "pfte-batch-1",
            "pfte-batch-1",
            "pfte-batch-1",
            "pfte-batch-1",
            "pfte-batch-1",
            "pfte-batch-1",
            "pfte-batch-1",
            "pfte-batch-1",
            "pfte-batch-1",
            "pfte-batch-1",
            "pfte-batch-1",
            "pfte-batch-1",
            "pfte-batch-1",
            "pfte-batch-1",
            "pfte-batch-1",
            "pfte-batch-1",
            "pfte-batch-1",
            "pfte-batch-1",
            "pfte-batch-1",
            "pfte-batch-1",
            "pfte-batch-1",
            "pfte-batch-1",
            "pfte-batch-1",
            "pfte-batch-1",
            "pfte-batch-1",
            "pfte-batch-1",
            "pfte-batch-1",
            "pfte-batch-1",
            "pfte-batch-1",
            "pfte-batch-1",
            "pfte-batch-1",
            "pfte-batch-1",
            "pfte-batch-1",
            "pfte-batch-1",
            "pfte-batch-1",
            "pfte-batch-1",
            "pfte-batch-1",
            "pfte-batch-1",
            "pfte-batch-1",
            "pfte-batch-1",
            "pfte-batch-1",
            "pfte-batch-1",
            "pfte-batch-1",
            "pfte-batch-1",
            "pfte-batch-1",
            "pfte-batch-1",
            "pfte-batch-1",
            "pfte-batch-1",
            "pfte-batch-1",
            "pfte-batch-1",
            "pfte-batch-1",
            "pfte-batch-1",
            "pfte-batch-1",
            "pfte-batch-1",
            "pfte-batch-1",
            "pfte-batch-1",
            "pfte-batch-1",
            "pfte-batch-1",
            "pfte-batch-1",
            "pfte-batch-1",
            "pfte-batch-1",
            "pfte-batch-1",
            "pfte-batch-1",
            "pfte-batch-1",
            "pfte-batch-1",
            "pfte-batch-1",
            "pfte-batch-1",
            "pfte-batch-1",
            "pfte-batch-1",
            "pfte-batch-1",
            "pfte-batch-1",
            "pfte-batch-1",
            "pfte-batch-1",
            "pfte-batch-1",
            "pfte-batch-1",
            "pfte-batch-1",
            "pfte-batch-1",
            "pfte-batch-1",
            "pfte-batch-1",
            "pfte-batch-1",
            "pfte-batch-1",
            "pfte-batch-1",
            "pfte-batch-1",
            "pfte-batch-1",
            "pfte-batch-1",
            "pfte-batch-1",
            "pfte-batch-1",
            "pfte-batch-1",
            "pfte-batch-1",
            "pfte-batch-1",
            "pfte-batch-1",
            "pfte-batch-1",
            "pfte-batch-1",
            "pfte-batch-1",
            "pfte-batch-1",
            "pfte-batch-1",
            "pfte-batch-1",
            "pfte-batch-1",
            "pfte-batch-1",
            "pfte-batch-1",
            "pfte-batch-1",
            "pfte-batch-1",
            "pfte-batch-1",
            "pfte-batch-1",
            "pfte-batch-1",
            "pfte-batch-1",
            "pfte-batch-1",
            "pfte-batch-1",
            "pfte-batch-1",
            "pfte-batch-1",
            "pfte-batch-1",
            "pfte-batch-1",
            "pfte-batch-1",
            "pfte-batch-1",
            "pfte-batch-1",
            "pfte-batch-1",
            "pfte-batch-1",
            "pfte-batch-1",
            "pfte-batch-1",
            "pfte-batch-1",
            "pfte-batch-1",
            "pfte-batch-1",
            "pfte-batch-1",
            "pfte-batch-1",
            "pfte-batch-1",
            "pfte-batch-1",
            "pfte-batch-1",
            "pfte-batch-1",
            "pfte-batch-1",
            "pfte-batch-1",
            "pfte-batch-1",
            "pfte-batch-1",
            "pfte-batch-1",
            "pfte-batch-1",
            "pfte-batch-1",
            "pfte-batch-1",
            "pfte-batch-1",
            "pfte-batch-1",
            "pfte-batch-1",
            "pfte-batch-1",
            "pfte-batch-1",
            "pfte-batch-1",
            "pfte-batch-1",
            "pfte-batch-1",
            "pfte-batch-1",
            "pfte-batch-1",
            "pfte-batch-1",
            "pfte-batch-1",
            "pfte-batch-1",
            "pfte-batch-1",
            "pfte-batch-1",
            "pfte-batch-1",
            "pfte-batch-1",
            "pfte-batch-1",
            "pfte-batch-1",
            "pfte-batch-1",
            "pfte-batch-1",
            "pfte-batch-1",
            "pfte-batch-1",
            "pfte-batch-1",
            "pfte-batch-1",
            "pfte-batch-1",
            "pfte-batch-1",
            "pfte-batch-1",
            "pfte-batch-1",
            "pfte-batch-1",
            "pfte-batch-1",
            "pfte-batch-1",
            "pfte-batch-1",
            "pfte-batch-1",
            "pfte-batch-1",
            "pfte-batch-1",
            "pfte-batch-1",
            "pfte-batch-1",
            "pfte-batch-1",
            "pfte-batch-1",
            "pfte-batch-1",
            "pfte-batch-1",
            "pfte-batch-1",
            "pfte-batch-1",
            "pfte-batch-1",
            "pfte-batch-1",
            "pfte-batch-1",
            "pfte-batch-1",
            "pfte-batch-1",
            "pfte-batch-1",
            "pfte-batch-1",
            "pfte-batch-1",
            "pfte-batch-1",
            "pfte-batch-1",
            "pfte-batch-1",
            "pfte-batch-1",
            "pfte-batch-1",
            "pfte-batch-1",
            "pfte-batch-1",
            "pfte-batch-1",
            "pfte-batch-1",
            "pfte-batch-1",
            "pfte-batch-1",
            "pfte-batch-1",
            "pfte-batch-1",
            "pfte-batch-1",
            "pfte-batch-1",
            "pfte-batch-1",
            "pfte-batch-1",
            "pfte-batch-1",
            "pfte-batch-1",
            "pfte-batch-1",
            "pfte-batch-1",
            "pfte-batch-1",
            "pfte-batch-1",
            "pfte-batch-1"
        ],
        "object_marking_refs": [
            "marking-definition--613f2e26-407d-48c7-9eca-b8e91df99dc9"
        ]
    }
]