[
    {
        "type": "infrastructure",
        "spec_version": "2.1",
        "id": "infrastructure--0552ba3e-0d62-4868-83dc-f98c41c5eded",
        "created_by_ref": "identity--f8d34e5b-fbf0-451c-9fa3-d1312372bef5",
        "created": "2021-03-14T16:26:30.75666Z",
        "modified": "2021-08-14T01:08:39.692094Z",
        "name": "clear",
        "infrastructure_types": [
            "command-and-control"
        ],
        "aliases": [
            "including"
        ],
        "first_seen": "2021-12-10T06:00:38.844653Z",
        "labels": [
            "pfte-batch-1"
        ],
        "lang": "en",
        "object_marking_refs": [
            "marking-definition--613f2e26-407d-48c7-9eca-b8e91df99dc9"
        ]
    },
    {
        "type": "ipv4-addr",
        "spec_version": "2.1",
        "id": "ipv4-addr--a1c94911-26bb-4cf5-b86e-0ad8708fb809",
        "value": "173.234.125.228",
        "labels": [
            "pfte-batch-1"
        ],
        "object_marking_refs": [
            "marking-definition--613f2e26-407d-48c7-9eca-b8e91df99dc9"
        ]
    },
    {
        "type": "relationship",
        "spec_version": "2.1",
        "id": "relationship--8ac9e517-a86c-4cce-8d8b-61339e8477ed",
        "created_by_ref": "identity--f8d34e5b-fbf0-451c-9fa3-d1312372bef5",
        "created": "2021-10-09T03:11:12.554417Z",
        "modified": "2022-03-30T02:24:46.57383Z",
        "relationship_type": "communicates-with",
        "description": "Film me husband will. Sometimes focus sell on future many this already. Perform three show gas however interesting manager we.",
        "source_ref": "infrastructure--0552ba3e-0d62-4868-83dc-f98c41c5eded",
        "target_ref": "ipv4-addr--a1c94911-26bb-4cf5-b86e-0ad8708fb809",
        "start_time": "2022-06-18T20:07:13.584505Z",
        "labels": [
            "pfte-batch-1"
        ],
        "confidence": 76,
        "lang": "en",
        "external_references": [
            {
                "source_name": "much",
                "url": "https://www.snyder.com/",
                "hashes": {
                    "MD5": "decfd21b91c7c34e77f9d2a41a90332f",
                    "SHA-1": "9775ffb6f6644e1423c800c5e9f83e7670fe66fa",
                    "SHA-256": "de41c340947d28d302a5f9f480b52e7e59c0e3a6d0e5e2b3daba10d59b94e251",
                    "SHA-512": "05bf2a8f77401150cb960c9d671f13dcab91a046c92efafd538dd556ace818f849fcfe3d45d6dd96df9bdff34c4802ed3a2b4d6a9eeafda5fc339f6b5f9dfc3d",
                    "SHA3-256": "e3352a141454918ff60398ce88cd37fcb54df9ba7d842614c99da6449d7d39a7",
                    "SHA3-512": "c69c49d4705110bf0525c8315fbd4d39f6e2b54fa76bb4a666c5800c7d3b5b250a7a72d1b322ddd458b006bca5308ef28ed2517a1c6745a0900db71a6591db6d"
                },
                "external_id": "XMsCKCDukAlVMXUAcbDm"
            },
            {
                "source_name": "nice",
                "description": "Station off Mr now possible office personal.",
                "hashes": {
                    "MD5": "330ed0a01173d2f6b0fdc5ff1cd584f9",
                    "SHA-1": "2ef22d7163904e6bf006dc66bd39901eeb301dd2",
                    "SHA-256": "d109162fec0b77d24cd29733821d7cc4165315f5e8241056db5e41a8d27e8c47",
                    "SHA-512": "1a55cdcd0eb80c8ac533612d189b2310ff9ac3ab0b2923e32e8bf7d3fb092adc195ce863a9121d9760057707eb3d96b4aa35e06b3a4a08dc696be0d3b9b8a074",
                    "SHA3-256": "f9b9253ca6ce07fec1455ff999dd3d247d28c0061fbbfcfca77073476468de17",
                    "SHA3-512": "8853d74d3cf2c10fa61d50194eee692a36990b28b664e6daefaf9a50c1053a0c949c256ddaa36d9a3561e30627cebf63d7d3ef01aac5d3e52b9fd076f2e2ce58"
                },
                "external_id": "QmCXMJwxIApMN"
            },
            {
                "source_name": "control",
                "description": "Soldier here defense guy nor sea kid."
            }
        ],
        "object_marking_refs": [
            "marking-definition--613f2e26-407d-48c7-9eca-b8e91df99dc9"
        ]
    },
    {
        "type": "identity",
        "spec_version": "2.1",
        "id": "identity--f8d34e5b-fbf0-451c-9fa3-d1312372bef5",
        "created_by_ref": "identity--b3bca3c2-1f3d-4b54-b44f-dac42c3a8f01",
        "created": "2020-01-01T00:00:00.000Z",
        "modified": "2020-01-01T00:00:00.000Z",
        "name": "USA.USG",
        "identity_class": "organization",
        "labels": [
            "ais-consent-everyone",
            "pfte-batch-1",
            "pfte-batch-1",
            "pfte-batch-1",
            "pfte-batch-1",
            "pfte-batch-1",
            "pfte-batch-1",
            "pfte-batch-1",
            "pfte-batch-1",
            "pfte-batch-1",
            "pfte-batch-1",
            "pfte-batch-1",
            "pfte-batch-1",
            "pfte-batch-1",
            "pfte-batch-1",
            "pfte-batch-1",
            "pfte-batch-1",
            "pfte-batch-1",
            "pfte-batch-1",
            "pfte-batch-1",
            "pfte-batch-1",
            "pfte-batch-1",
            "pfte-batch-1",
            "pfte-batch-1",
            "pfte-batch-1",
            "pfte-batch-1",
            "pfte-batch-1",
            "pfte-batch-1",
            "pfte-batch-1",
            "pfte-batch-1",
            "pfte-batch-1",
            "pfte-batch-1",
            "pfte-batch-1",
            "pfte-batch-1",
            "pfte-batch-1",
            "pfte-batch-1",
            "pfte-batch-1",
            "pfte-batch-1",
            "pfte-batch-1",
            "pfte-batch-1",
            "pfte-batch-1",
            "pfte-batch-1",
            "pfte-batch-1",
            "pfte-batch-1",
            "pfte-batch-1",
            "pfte-batch-1",
            "pfte-batch-1",
            "pfte-batch-1",
            "pfte-batch-1",
            "pfte-batch-1",
            "pfte-batch-1",
            "pfte-batch-1",
            "pfte-batch-1",
            "pfte-batch-1",
            "pfte-batch-1",
            "pfte-batch-1",
            "pfte-batch-1",
            "pfte-batch-1",
            "pfte-batch-1",
            "pfte-batch-1",
            "pfte-batch-1",
            "pfte-batch-1",
            "pfte-batch-1",
            "pfte-batch-1",
            "pfte-batch-1",
            "pfte-batch-1",
            "pfte-batch-1",
            "pfte-batch-1",
            "pfte-batch-1",
            "pfte-batch-1",
            "pfte-batch-1",
            "pfte-batch-1",
            "pfte-batch-1",
            "pfte-batch-1",
            "pfte-batch-1",
            "pfte-batch-1",
            "pfte-batch-1",
            "pfte-batch-1",
            "pfte-batch-1",
            "pfte-batch-1",
            "pfte-batch-1",
            "pfte-batch-1",
            "pfte-batch-1",
            "pfte-batch-1",
            "pfte-batch-1",
            "pfte-batch-1",
            "pfte-batch-1",
            "pfte-batch-1",
            "pfte-batch-1",
            "pfte-batch-1",
            "pfte-batch-1",
            "pfte-batch-1",
            "pfte-batch-1",
            "pfte-batch-1",
            "pfte-batch-1",
            "pfte-batch-1",
            "pfte-batch-1",
            "pfte-batch-1",
            "pfte-batch-1",
            "pfte-batch-1",
            "pfte-batch-1",
            "pfte-batch-1",
            "pfte-batch-1",
            "pfte-batch-1",
            "pfte-batch-1",
            "pfte-batch-1",
            "pfte-batch-1",
            "pfte-batch-1",
            "pfte-batch-1",
            "pfte-batch-1",
            "pfte-batch-1",
            "pfte-batch-1",
            "pfte-batch-1",
            "pfte-batch-1",
            "pfte-batch-1",
            "pfte-batch-1",
            "pfte-batch-1",
            "pfte-batch-1",
            "pfte-batch-1",
            "pfte-batch-1",
            "pfte-batch-1",
            "pfte-batch-1",
            "pfte-batch-1",
            "pfte-batch-1",
            "pfte-batch-1",
            "pfte-batch-1",
            "pfte-batch-1",
            "pfte-batch-1",
            "pfte-batch-1",
            "pfte-batch-1",
            "pfte-batch-1",
            "pfte-batch-1",
            "pfte-batch-1",
            "pfte-batch-1",
            "pfte-batch-1",
            "pfte-batch-1",
            "pfte-batch-1",
            "pfte-batch-1",
            "pfte-batch-1",
            "pfte-batch-1",
            "pfte-batch-1",
            "pfte-batch-1",
            "pfte-batch-1",
            "pfte-batch-1",
            "pfte-batch-1",
            "pfte-batch-1",
            "pfte-batch-1",
            "pfte-batch-1",
            "pfte-batch-1",
            "pfte-batch-1",
            "pfte-batch-1",
            "pfte-batch-1",
            "pfte-batch-1",
            "pfte-batch-1",
            "pfte-batch-1",
            "pfte-batch-1",
            "pfte-batch-1",
            "pfte-batch-1",
            "pfte-batch-1",
            "pfte-batch-1",
            "pfte-batch-1",
            "pfte-batch-1",
            "pfte-batch-1",
            "pfte-batch-1",
            "pfte-batch-1",
            "pfte-batch-1",
            "pfte-batch-1",
            "pfte-batch-1",
            "pfte-batch-1",
            "pfte-batch-1",
            "pfte-batch-1",
            "pfte-batch-1",
            "pfte-batch-1",
            "pfte-batch-1",
            "pfte-batch-1",
            "pfte-batch-1",
            "pfte-batch-1",
            "pfte-batch-1",
            "pfte-batch-1",
            "pfte-batch-1",
            "pfte-batch-1",
            "pfte-batch-1",
            "pfte-batch-1",
            "pfte-batch-1",
            "pfte-batch-1",
            "pfte-batch-1",
            "pfte-batch-1",
            "pfte-batch-1",
            "pfte-batch-1",
            "pfte-batch-1",
            "pfte-batch-1",
            "pfte-batch-1",
            "pfte-batch-1",
            "pfte-batch-1",
            "pfte-batch-1",
            "pfte-batch-1",
            "pfte-batch-1",
            "pfte-batch-1",
            "pfte-batch-1",
            "pfte-batch-1",
            "pfte-batch-1",
            "pfte-batch-1",
            "pfte-batch-1",
            "pfte-batch-1",
            "pfte-batch-1",
            "pfte-batch-1",
            "pfte-batch-1",
            "pfte-batch-1",
            "pfte-batch-1",
            "pfte-batch-1",
            "pfte-batch-1",
            "pfte-batch-1",
            "pfte-batch-1",
            "pfte-batch-1",
            "pfte-batch-1",
            "pfte-batch-1",
            "pfte-batch-1",
            "pfte-batch-1",
            "pfte-batch-1",
            "pfte-batch-1",
            "pfte-batch-1",
            "pfte-batch-1",
            "pfte-batch-1",
            "pfte-batch-1",
            "pfte-batch-1",
            "pfte-batch-1",
            "pfte-batch-1",
            "pfte-batch-1",
            "pfte-batch-1",
            "pfte-batch-1",
            "pfte-batch-1",
            "pfte-batch-1",
            "pfte-batch-1",
            "pfte-batch-1",
            "pfte-batch-1",
            "pfte-batch-1",
            "pfte-batch-1",
            "pfte-batch-1",
            "pfte-batch-1",
            "pfte-batch-1",
            "pfte-batch-1",
            "pfte-batch-1",
            "pfte-batch-1",
            "pfte-batch-1",
            "pfte-batch-1",
            "pfte-batch-1",
            "pfte-batch-1",
            "pfte-batch-1",
            "pfte-batch-1",
            "pfte-batch-1",
            "pfte-batch-1",
            "pfte-batch-1",
            "pfte-batch-1",
            "pfte-batch-1",
            "pfte-batch-1",
            "pfte-batch-1",
            "pfte-batch-1",
            "pfte-batch-1",
            "pfte-batch-1",
            "pfte-batch-1",
            "pfte-batch-1",
            "pfte-batch-1",
            "pfte-batch-1",
            "pfte-batch-1",
            "pfte-batch-1",
            "pfte-batch-1",
            "pfte-batch-1",
            "pfte-batch-1",
            "pfte-batch-1",
            "pfte-batch-1",
            "pfte-batch-1",
            "pfte-batch-1",
            "pfte-batch-1",
            "pfte-batch-1",
            "pfte-batch-1",
            "pfte-batch-1",
            "pfte-batch-1",
            "pfte-batch-1",
            "pfte-batch-1",
            "pfte-batch-1",
            "pfte-batch-1",
            "pfte-batch-1",
            "pfte-batch-1",
            "pfte-batch-1",
            "pfte-batch-1",
            "pfte-batch-1",
            "pfte-batch-1",
            "pfte-batch-1",
            "pfte-batch-1",
            "pfte-batch-1",
            "pfte-batch-1",
            "pfte-batch-1",
            "pfte-batch-1",
            "pfte-batch-1",
            "pfte-batch-1",
            "pfte-batch-1",
            "pfte-batch-1",
            "pfte-batch-1",
            "pfte-batch-1",
            "pfte-batch-1",
            "pfte-batch-1",
            "pfte-batch-1",
            "pfte-batch-1",
            "pfte-batch-1",
            "pfte-batch-1",
            "pfte-batch-1",
            "pfte-batch-1",
            "pfte-batch-1",
            "pfte-batch-1",
            "pfte-batch-1",
            "pfte-batch-1",
            "pfte-batch-1",
            "pfte-batch-1",
            "pfte-batch-1",
            "pfte-batch-1",
            "pfte-batch-1",
            "pfte-batch-1",
            "pfte-batch-1",
            "pfte-batch-1",
            "pfte-batch-1",
            "pfte-batch-1",
            "pfte-batch-1",
            "pfte-batch-1",
            "pfte-batch-1",
            "pfte-batch-1",
            "pfte-batch-1",
            "pfte-batch-1",
            "pfte-batch-1",
            "pfte-batch-1",
            "pfte-batch-1",
            "pfte-batch-1",
            "pfte-batch-1",
            "pfte-batch-1",
            "pfte-batch-1",
            "pfte-batch-1",
            "pfte-batch-1",
            "pfte-batch-1",
            "pfte-batch-1",
            "pfte-batch-1",
            "pfte-batch-1",
            "pfte-batch-1",
            "pfte-batch-1",
            "pfte-batch-1",
            "pfte-batch-1",
            "pfte-batch-1",
            "pfte-batch-1",
            "pfte-batch-1",
            "pfte-batch-1",
            "pfte-batch-1",
            "pfte-batch-1",
            "pfte-batch-1",
            "pfte-batch-1",
            "pfte-batch-1",
            "pfte-batch-1",
            "pfte-batch-1",
            "pfte-batch-1",
            "pfte-batch-1",
            "pfte-batch-1",
            "pfte-batch-1",
            "pfte-batch-1",
            "pfte-batch-1",
            "pfte-batch-1",
            "pfte-batch-1",
            "pfte-batch-1",
            "pfte-batch-1",
            "pfte-batch-1",
            "pfte-batch-1",
            "pfte-batch-1",
            "pfte-batch-1",
            "pfte-batch-1",
            "pfte-batch-1",
            "pfte-batch-1",
            "pfte-batch-1",
            "pfte-batch-1",
            "pfte-batch-1",
            "pfte-batch-1",
            "pfte-batch-1",
            "pfte-batch-1",
            "pfte-batch-1",
            "pfte-batch-1",
            "pfte-batch-1",
            "pfte-batch-1",
            "pfte-batch-1",
            "pfte-batch-1",
            "pfte-batch-1",
            "pfte-batch-1",
            "pfte-batch-1",
            "pfte-batch-1",
            "pfte-batch-1",
            "pfte-batch-1",
            "pfte-batch-1",
            "pfte-batch-1",
            "pfte-batch-1",
            "pfte-batch-1",
            "pfte-batch-1",
            "pfte-batch-1",
            "pfte-batch-1",
            "pfte-batch-1",
            "pfte-batch-1",
            "pfte-batch-1",
            "pfte-batch-1",
            "pfte-batch-1",
            "pfte-batch-1",
            "pfte-batch-1",
            "pfte-batch-1",
            "pfte-batch-1"
        ],
        "object_marking_refs": [
            "marking-definition--613f2e26-407d-48c7-9eca-b8e91df99dc9"
        ]
    }
]