[
    {
        "confidence": 56,
        "created": "2021-02-03T12:26:00.094352Z",
        "created_by_ref": "identity--dbe5b8d1-7fe0-4bec-b5b1-8dcbeb7b2879",
        "description": "Seamless eco-centric installation",
        "id": "identity--dbe5b8d1-7fe0-4bec-b5b1-8dcbeb7b2879",
        "identity_class": "class",
        "modified": "2021-08-14T01:08:21.917581Z",
        "name": "Smith-Warren",
        "object_marking_refs": [
            "marking-definition--da4f7162-ce1c-4172-9693-45efd33a5ea7"
        ],
        "sectors": [
            "automotive",
            "education",
            "defense",
            "hospitality-leisure"
        ],
        "spec_version": "2.1",
        "type": "identity",
        "labels": [
            "pfte-batch-1"
        ]
    },
    {
        "created": "2021-01-12T06:46:49.168651Z",
        "created_by_ref": "identity--dbe5b8d1-7fe0-4bec-b5b1-8dcbeb7b2879",
        "description": "Western spend son area baby form.",
        "external_references": [
            {
                "description": "Maintain early describe walk measure training ground.",
                "external_id": "FzXpNsJjvaIDf",
                "hashes": {
                    "MD5": "df8ccb4ae9bfb548975502f046181e50",
                    "SHA-1": "cc72e352b19b68be3cac1cb6feae43096768db12",
                    "SHA-256": "ecd7c82e650a665cf0c5b50421aafa7beaa834fe3482b1709d49c10fe0206bbc",
                    "SHA-512": "ab8e15b19d60956dde76e5b8e80abe15ca53b086189745c33a784f6a33f9a06527f969a14d8d4cbbbea5417dc1ce69ab10dbb156770cc9fddec04914a59f8784",
                    "SHA3-256": "d636fef9ff097ca68783dcffe8f1ab685b18bc8acc2deb2d8ec827c711edc1f5",
                    "SHA3-512": "5e7b247e16ab75bb0821ccf64d40e2b68f48cfb242cd94c0682d57a222daa1e10c97ff5ba327cb3727952e117a1ba77ac3ca6ff2158f7f79e4de44547013a32d"
                },
                "source_name": "until",
                "url": "http://marshall.com/"
            }
        ],
        "id": "course-of-action--1cf5e7b4-12fa-4b1a-9044-b00704d7059c",
        "modified": "2022-01-08T08:26:18.549143Z",
        "name": "trip",
        "object_marking_refs": [
            "marking-definition--da4f7162-ce1c-4172-9693-45efd33a5ea7"
        ],
        "spec_version": "2.1",
        "type": "course-of-action",
        "labels": [
            "pfte-batch-1"
        ]
    },
    {
        "created": "2022-04-25T14:57:00.263684Z",
        "created_by_ref": "identity--dbe5b8d1-7fe0-4bec-b5b1-8dcbeb7b2879",
        "description": "Scene garden side.",
        "external_references": [
            {
                "description": "Raise everybody together role.",
                "external_id": "BmshZyjohOUE",
                "hashes": {
                    "MD5": "33448e2dc12fcb99396832769b82fbb4",
                    "SHA-1": "2190f60a67c2c794919b788532b66383f369e8e5",
                    "SHA-256": "6e4c513b73399eef5380948acda3da6f54f7c5e00eb4a0335fe17f9c9eb308cb",
                    "SHA-512": "081cc578001b994f75eefc038c5d040890d154cbabdd260ea186a72a676731afea471bb3b4787d00f6d1011bb26c3ccef6be52393c1666142491d488f25b2962",
                    "SHA3-256": "9a2634d2a1962084e8d1d350a363967edc1e152ca4f61f616a54a877f2c52e27",
                    "SHA3-512": "9c5c11a6581a9e2e68ba5fd2dc807af0ca16028d74b5a9d4824d25b984129bbc1104317a663f5b1eee5f7aa179f14efef7c7fa68a2c3310a4aed44fa22879f40"
                },
                "source_name": "firm"
            },
            {
                "description": "Those me require young.",
                "source_name": "around",
                "url": "http://nelson.biz/"
            },
            {
                "source_name": "control",
                "url": "http://quinn.com/"
            }
        ],
        "id": "indicator--2dd1d338-5fec-4263-aab7-c52dc6b64568",
        "indicator_types": [
            "unknown"
        ],
        "labels": [
            "condition",
            "guy",
            "exist",
            "pfte-batch-1"
        ],
        "lang": "en",
        "modified": "2022-07-05T16:46:33.028573Z",
        "name": "place",
        "object_marking_refs": [
            "marking-definition--da4f7162-ce1c-4172-9693-45efd33a5ea7"
        ],
        "pattern": "[ipv4-addr:value <= '18.89.22.225']",
        "pattern_type": "stix",
        "pattern_version": "2.1",
        "spec_version": "2.1",
        "type": "indicator",
        "valid_from": "2021-06-10T19:45:18.956417Z",
        "valid_until": "2022-01-17T13:43:45.243198Z"
    },
    {
        "confidence": 59,
        "created": "2022-01-16T06:23:33.140938Z",
        "created_by_ref": "identity--dbe5b8d1-7fe0-4bec-b5b1-8dcbeb7b2879",
        "id": "relationship--173e6884-bbdc-45a6-b8b0-6b2295a489e6",
        "labels": [
            "rate",
            "pfte-batch-1"
        ],
        "lang": "en",
        "modified": "2022-02-08T22:09:42.69482Z",
        "object_marking_refs": [
            "marking-definition--da4f7162-ce1c-4172-9693-45efd33a5ea7"
        ],
        "relationship_type": "investigates",
        "source_ref": "course-of-action--1cf5e7b4-12fa-4b1a-9044-b00704d7059c",
        "spec_version": "2.1",
        "stop_time": "2022-04-25T02:05:46.720714Z",
        "target_ref": "indicator--2dd1d338-5fec-4263-aab7-c52dc6b64568",
        "type": "relationship"
    },
    {
        "created": "2021-08-14T01:08:21.914856Z",
        "created_by_ref": "identity--dbe5b8d1-7fe0-4bec-b5b1-8dcbeb7b2879",
        "extensions": {
            "extension-definition--3a65884d-005a-4290-8335-cb2d778a83ce": {
                "authority_reference": [
                    "urn:isa:authority:misa"
                ],
                "control_set": {
                    "classification": "U",
                    "formal_determination": [
                        "PUBREL"
                    ]
                },
                "create_date_time": "2021-08-14T01:08:08.425512Z",
                "extension_type": "property-extension",
                "further_sharing": [
                    {
                        "rule_effect": "permit",
                        "sharing_scope": [
                            "USA.USG"
                        ]
                    }
                ],
                "identifier": "isa:guide.19001.ACS3-7fb4e63d-338f-4f0a-b771-dd937b9aaabe",
                "name": "Human on join spring",
                "policy_reference": "urn:isa:policy:acs:ns:v3.0?privdefault=permit&sharedefault=permit",
                "public_release": {
                    "released_by": "USA.DHS.US-CERT",
                    "released_on": "2021-08-14T01:08:08.425314Z"
                },
                "responsible_entity_custodian": "USA.DHS.US-CERT",
                "responsible_entity_originator": "USA.DHS.NCCIC"
            }
        },
        "id": "marking-definition--da4f7162-ce1c-4172-9693-45efd33a5ea7",
        "spec_version": "2.1",
        "type": "marking-definition"
    },
    {
        "aliases": [
            "car",
            "half",
            "push",
            "order"
        ],
        "confidence": 94,
        "created": "2022-02-13T07:05:08.754724Z",
        "created_by_ref": "identity--dbe5b8d1-7fe0-4bec-b5b1-8dcbeb7b2879",
        "description": "Day enjoy two them direction leg.",
        "id": "campaign--fb6333dd-d5b6-4059-91d9-2f3ede13d475",
        "labels": [
            "water",
            "school",
            "debate",
            "pfte-batch-1"
        ],
        "last_seen": "2022-07-14T17:48:34.531376Z",
        "modified": "2022-03-06T04:22:34.83991Z",
        "name": "activity",
        "object_marking_refs": [
            "marking-definition--da4f7162-ce1c-4172-9693-45efd33a5ea7"
        ],
        "objective": "Various community various different sense race.",
        "spec_version": "2.1",
        "type": "campaign"
    },
    {
        "confidence": 82,
        "created": "2021-11-06T01:25:41.427794Z",
        "created_by_ref": "identity--dbe5b8d1-7fe0-4bec-b5b1-8dcbeb7b2879",
        "description": "Customer across cultural moment walk might. Billion situation space.",
        "external_references": [
            {
                "description": "Trip son able.",
                "external_id": "usdfwlIaIl",
                "hashes": {
                    "MD5": "08446ee621faa8af0927e06f8b206a55",
                    "SHA-1": "7ed8ff00730511ac274d1744adff38ad952d3634",
                    "SHA-256": "c278526caa2504fe8efdc0d90e23ee2209b432ae959d9d6d08364df580ce1ed1",
                    "SHA-512": "106f6887fdb218f65d61b072fcdc1a3dfa2ebd38b71144957eb64daf6b582896d0324f5f55262d1ec321909a93a7309dbd3b2c673346ae6ee78211878668318d",
                    "SHA3-256": "4e980e4866f28c67d0611df26c0691dbd9dc346a54bad8dd0a1eb628e1424799",
                    "SHA3-512": "81a82412fd844865f96de324dfc1244bd9f5e1ef0ed2bdbd9f6153527c0cb6e6aa69e5835e274b78742f9bf66e2a5ae7cefc20b4257a1cdff244ec9cebcef432"
                },
                "source_name": "develop",
                "url": "https://daniels.org/"
            },
            {
                "description": "By population form eat.",
                "source_name": "state"
            }
        ],
        "id": "relationship--2194da3b-c45b-47dd-ac58-6cf603d6611a",
        "lang": "en",
        "modified": "2022-04-30T01:01:12.569712Z",
        "object_marking_refs": [
            "marking-definition--da4f7162-ce1c-4172-9693-45efd33a5ea7"
        ],
        "relationship_type": "indicates",
        "source_ref": "indicator--2dd1d338-5fec-4263-aab7-c52dc6b64568",
        "spec_version": "2.1",
        "stop_time": "2021-12-15T02:06:59.742403Z",
        "target_ref": "campaign--fb6333dd-d5b6-4059-91d9-2f3ede13d475",
        "type": "relationship",
        "labels": [
            "pfte-batch-1"
        ]
    },
    {
        "confidence": 86,
        "created": "2021-01-31T19:41:20.688194Z",
        "created_by_ref": "identity--dbe5b8d1-7fe0-4bec-b5b1-8dcbeb7b2879",
        "external_references": [
            {
                "description": "Understand much analysis name them important.",
                "source_name": "one",
                "url": "http://mcintyre.com/"
            }
        ],
        "goals": [
            "Partner ready person ago.",
            "Through season center you.",
            "Music own just bar when section box."
        ],
        "id": "intrusion-set--dd612399-4e2d-4d3f-910d-5968dc054e08",
        "modified": "2021-10-03T02:10:50.481773Z",
        "name": "hit",
        "object_marking_refs": [
            "marking-definition--da4f7162-ce1c-4172-9693-45efd33a5ea7"
        ],
        "resource_level": "team",
        "spec_version": "2.1",
        "type": "intrusion-set",
        "labels": [
            "pfte-batch-1"
        ]
    },
    {
        "created": "2022-01-07T12:18:34.303282Z",
        "created_by_ref": "identity--dbe5b8d1-7fe0-4bec-b5b1-8dcbeb7b2879",
        "description": "Ago education stay capital series attention recently because. Season for nature rate agent.",
        "external_references": [
            {
                "external_id": "gTdwiKewFMQRaoxJgD",
                "source_name": "traditional",
                "url": "https://owens.com/"
            },
            {
                "external_id": "PbvfltsAAXgDpQWUfcz",
                "hashes": {
                    "MD5": "acc6623f545aab0ba289419b1cad70fa",
                    "SHA-1": "26f8c6709d986ae37e3f5b1ff96f49579c816382",
                    "SHA-256": "28b333af5287a2a8a80f1a31ec0a82609e596a9127cf348450bfe4cf0dcee0ca",
                    "SHA-512": "a1bbff14d6c14092578884688732800bc2b558c828bc0b1f16cad90da282faf1402706612b535b1e74aa09839c5a61c42349414c6be8bce4b2935441cb62a217",
                    "SHA3-256": "c0fc08151bf3914f30fe0da8d7f0384ab2eef7f8fd77566daad1bf312e8d5511",
                    "SHA3-512": "97623a9ec6b7aa2ec1c2c503e70853435e04ef02b8b140000db06fe10b0af2ec96d8eed3783fba1cb2373b7828628eed855b6e05413368456cf7c8e00b378683"
                },
                "source_name": "fish",
                "url": "https://www.roberts-sanders.com/"
            },
            {
                "hashes": {
                    "MD5": "dea9d50a05bd8b66b5adf60d493abf87",
                    "SHA-1": "31cfbfc2d34f9eedf78596a3e75b0e9cde05d462",
                    "SHA-256": "51baec575a47e6628fff9ff33fc0d6ca1885f9e3f06446213a887a51641c2dd7",
                    "SHA-512": "bbbd703cb62f4aea74e5cdf7c4696a8e6bac9833de3d3469cfa05fcc13c1b5f32261488f15d4ef95c2ffe6467503d9d7845eb8fcd7dd87916bd545590f197ff0",
                    "SHA3-256": "e3fff70ab584b781c1daaeab9e94f790f4d4f49846a8d226b6d9fefe1608a50a",
                    "SHA3-512": "547c1ad778826e1739131a787b9c2641f49062fff8927e66299530c4c329d278366e133e1f9fa313b8285d1d11f2faddd4c5d64cefae390ffc2d2880070ad18b"
                },
                "source_name": "detail",
                "url": "http://taylor-ford.com/"
            },
            {
                "description": "Above treatment middle whatever me improve century region.",
                "hashes": {
                    "MD5": "18d5a2a42b074dbdf6b8150386ca318d",
                    "SHA-1": "476cda24667bf12c3b682abcc66bf080f3801f41",
                    "SHA-256": "97641f9c1293b4a0847eb613ca47e1cc33c12276ea925aacfdb0aca5b23a0c94",
                    "SHA-512": "eaa36cf2c0546b54c9847da8320addc8bed4ec2fb52d1f2de8954703c1c02de22a58172f81a7418cda9c057adf450484839370c63fcbbbf8226a5a3a2ad18f55",
                    "SHA3-256": "2cfc65ff925bb7191a62247503ee986bdf3f714c39b1cdd6cf0345a9dcb6d137",
                    "SHA3-512": "5391048578e684f6076c72d5c0e5d0af69c90b9077b889a04c3351b224f4978317b90ad9ebe88bf41b7a5f687a41ffd072342251677be154616063bf7100c960"
                },
                "source_name": "long",
                "url": "https://www.clark.info/"
            },
            {
                "source_name": "front",
                "url": "https://www.meyers.biz/"
            }
        ],
        "id": "relationship--9f5c72df-cca1-4c30-98b9-52572efaa771",
        "modified": "2022-10-10T12:01:41.233458Z",
        "object_marking_refs": [
            "marking-definition--da4f7162-ce1c-4172-9693-45efd33a5ea7"
        ],
        "relationship_type": "attributed-to",
        "source_ref": "campaign--fb6333dd-d5b6-4059-91d9-2f3ede13d475",
        "spec_version": "2.1",
        "start_time": "2022-01-13T12:08:52.844269Z",
        "target_ref": "intrusion-set--dd612399-4e2d-4d3f-910d-5968dc054e08",
        "type": "relationship",
        "labels": [
            "pfte-batch-1"
        ]
    },
    {
        "confidence": 36,
        "created": "2022-07-18T13:57:28.685423Z",
        "created_by_ref": "identity--dbe5b8d1-7fe0-4bec-b5b1-8dcbeb7b2879",
        "description": "Sea listen nearly positive.",
        "id": "infrastructure--0c3b4251-73f4-48f5-9d29-448922a84e8d",
        "infrastructure_types": [
            "anonymization",
            "reconnaissance",
            "botnet"
        ],
        "kill_chain_phases": [
            {
                "kill_chain_name": "lockheed-martin-cyber-kill-chain",
                "phase_name": "installation"
            }
        ],
        "lang": "en",
        "modified": "2023-02-11T08:03:25.80317Z",
        "name": "born",
        "object_marking_refs": [
            "marking-definition--da4f7162-ce1c-4172-9693-45efd33a5ea7"
        ],
        "spec_version": "2.1",
        "type": "infrastructure",
        "labels": [
            "pfte-batch-1"
        ]
    },
    {
        "confidence": 24,
        "created": "2021-05-08T18:59:29.875064Z",
        "created_by_ref": "identity--dbe5b8d1-7fe0-4bec-b5b1-8dcbeb7b2879",
        "external_references": [
            {
                "description": "Address place myself dream.",
                "external_id": "KllNdlMZBJMgHTkG",
                "source_name": "keep",
                "url": "http://ross.com/"
            },
            {
                "description": "Whole you ask two.",
                "external_id": "SgOfFzs",
                "hashes": {
                    "MD5": "f8691be2e2951481e54a2374ea0bbb3d",
                    "SHA-1": "c43d6db483d685e11ef8d07a60581e2b712bfbef",
                    "SHA-256": "f7959fe525cfaac80ec4558ac9b98bfd21b48f5a0084e10beeabeb2d3861657f",
                    "SHA-512": "6152dfa6521458186a80e123fd4cc61bd99398239b9bed450fa650556ae71513e05e1071bd9d7a71e0a0b01f5ac2479cc9f53a1afd81105626b955140b9c9d0c",
                    "SHA3-256": "8bebda63326e67899da4f0a5b58853ba3a6e9fde04785fcde7ae241bca974891",
                    "SHA3-512": "bb6a95003af8824c5a63920a2b2396fe30ed3ae64388540c324c7cf619019ecec547f20ebee097638c859272e6b65123c71764c62ad9fb847474672ee0de8364"
                },
                "source_name": "job"
            },
            {
                "external_id": "CtmmDoEYQ",
                "source_name": "seem",
                "url": "https://harris.com/"
            },
            {
                "description": "Represent blue view off image.",
                "external_id": "dysuqPxwYpZO",
                "source_name": "myself",
                "url": "https://jimenez.com/"
            },
            {
                "description": "Security stage staff same.",
                "hashes": {
                    "MD5": "3ede1ccf43c3fb6d71f18526d53fffbc",
                    "SHA-1": "bf61d53dfd6f5373dbee3b26198acb2fb414d7aa",
                    "SHA-256": "6dc520a9d6589dedf7afb75e79936d4425c598d4ee401c0c1fdc28aa9f4ee404",
                    "SHA-512": "f9d5d882233b34f5e225ac58224e4e105f65240d2b6404d9f6fa698b3bb400effab1cdd481e94f086f5a3bf0bc327343e78af6538701a012c4b8cffff3ca9685",
                    "SHA3-256": "4f00e6c1b2b686bb4ace2e76539fe8804289b216f9e0724f91811415813f1a0f",
                    "SHA3-512": "77629e701795d4b2c57b534e6dbfd1f551ef3d9b327879b9a296cf8e10740d100dd7329249fdd7b478095516d7778d9f4652ac52c3ad250f87b26812b44e53cd"
                },
                "source_name": "half"
            }
        ],
        "id": "relationship--5e6d471f-c9ab-4347-9ea5-21ee9511c153",
        "labels": [
            "third",
            "fill",
            "hospital",
            "agreement",
            "we",
            "pfte-batch-1"
        ],
        "lang": "en",
        "modified": "2021-10-07T21:39:02.521907Z",
        "object_marking_refs": [
            "marking-definition--da4f7162-ce1c-4172-9693-45efd33a5ea7"
        ],
        "relationship_type": "owns",
        "source_ref": "intrusion-set--dd612399-4e2d-4d3f-910d-5968dc054e08",
        "spec_version": "2.1",
        "start_time": "2021-04-08T21:28:36.196997Z",
        "stop_time": "2021-09-08T17:42:33.694245Z",
        "target_ref": "infrastructure--0c3b4251-73f4-48f5-9d29-448922a84e8d",
        "type": "relationship"
    },
    {
        "aliases": [
            "believe",
            "show"
        ],
        "created": "2020-09-12T14:22:45.537505Z",
        "created_by_ref": "identity--dbe5b8d1-7fe0-4bec-b5b1-8dcbeb7b2879",
        "description": "Suddenly answer deal gun generation determine friend.",
        "id": "tool--2e506862-cee3-4f39-8719-950b7995de3c",
        "lang": "en",
        "modified": "2021-08-14T01:08:48.330391Z",
        "name": "majority",
        "object_marking_refs": [
            "marking-definition--da4f7162-ce1c-4172-9693-45efd33a5ea7"
        ],
        "spec_version": "2.1",
        "tool_version": "authority",
        "type": "tool",
        "labels": [
            "pfte-batch-1"
        ]
    },
    {
        "confidence": 75,
        "created": "2022-05-22T21:37:10.634595Z",
        "created_by_ref": "identity--dbe5b8d1-7fe0-4bec-b5b1-8dcbeb7b2879",
        "description": "Expert finish only now close. Plant get beautiful final live. Owner treatment hope general.",
        "external_references": [
            {
                "description": "Tree ability only garden area fear check stand.",
                "external_id": "vNNcmQI",
                "hashes": {
                    "MD5": "5d33d831492418a2de03b71cca3744ca",
                    "SHA-1": "638017e120b4408a44dd4ea36839efa9a6f6800e",
                    "SHA-256": "bbc379c1d18e4d221ba66b4183897b5ed7ca529335eb7140d927f83eb8c49b7d",
                    "SHA-512": "c891a27b1b6939b6111d2a845f2c291992b1e970d293a1aaf2c66b33e2ebb4583d9d3b7542cea9927dac222c40a4fb5d5e89f5603c1f59949749850f9a0d8edd",
                    "SHA3-256": "5e912afbc09671e9324f956cc2efc8173f532f20e4476125fa928d05ec414005",
                    "SHA3-512": "c130a0b1886652a21d03f08c5f0c8a8cdc5c72716b111dec97481f347ac97e07726e567bf23486360a1a320b9b8be05c07e4dffe2c828d2f82563ae4d9b3bf67"
                },
                "source_name": "later",
                "url": "http://www.yang.net/"
            }
        ],
        "id": "relationship--c4fbfe6f-1e39-437b-8a7d-89d0eb92215e",
        "modified": "2023-04-22T19:24:04.41907Z",
        "object_marking_refs": [
            "marking-definition--da4f7162-ce1c-4172-9693-45efd33a5ea7"
        ],
        "relationship_type": "hosts",
        "source_ref": "infrastructure--0c3b4251-73f4-48f5-9d29-448922a84e8d",
        "spec_version": "2.1",
        "start_time": "2022-01-20T20:20:39.348241Z",
        "target_ref": "tool--2e506862-cee3-4f39-8719-950b7995de3c",
        "type": "relationship",
        "labels": [
            "pfte-batch-1"
        ]
    },
    {
        "confidence": 33,
        "contact_information": "254 West Points Apt. 669\nSullivanland, NE 00795",
        "created": "2021-04-15T16:48:00.193014Z",
        "created_by_ref": "identity--dbe5b8d1-7fe0-4bec-b5b1-8dcbeb7b2879",
        "external_references": [
            {
                "external_id": "TAfRvWHUVVLVvHULiQvd",
                "source_name": "method",
                "url": "http://silva.info/"
            },
            {
                "description": "Book sister huge method.",
                "source_name": "campaign",
                "url": "http://obrien.com/"
            },
            {
                "hashes": {
                    "MD5": "e1be01a065d4c7b0df10c6e08979b609",
                    "SHA-1": "7eac25dcd6fc610afff9e905bb01a1ffe32e7f30",
                    "SHA-256": "5a4eef9c52624d7f23bac17846fbbd193e5952a5404865fcd76b594419df101b",
                    "SHA-512": "cd7b9f8b2f0ed66cd1ada0662370d20a3f20fa47dd16c1484b271df06bb050faf94a3cb8b6f70923be7c25172a55f0d314d523d686176d686d8623ea076e5d0e",
                    "SHA3-256": "8ae856d626917b603b943b3a5e07e6a1f5380608e19e7ee7bd90b1a4e6cda568",
                    "SHA3-512": "468c6d14d776d31f7dedbe5bf189dbeec250e771f92550b1f7382ce3e745edd7ba45db78b8cccefba2c5eb410ef9ac7e98a3b8e70f50f9098da01f72a246f458"
                },
                "source_name": "ago",
                "url": "http://mckinney.biz/"
            }
        ],
        "id": "identity--f31d8454-3e50-412e-8d21-5d827d02cf47",
        "labels": [
            "question",
            "off",
            "himself",
            "car",
            "move",
            "pfte-batch-1"
        ],
        "lang": "en",
        "modified": "2021-08-14T01:09:38.967019Z",
        "name": "Price LLC",
        "object_marking_refs": [
            "marking-definition--da4f7162-ce1c-4172-9693-45efd33a5ea7"
        ],
        "roles": [
            "themselves",
            "wish",
            "until",
            "itself",
            "successful"
        ],
        "spec_version": "2.1",
        "type": "identity"
    },
    {
        "created": "2021-12-23T23:21:44.986899Z",
        "created_by_ref": "identity--dbe5b8d1-7fe0-4bec-b5b1-8dcbeb7b2879",
        "description": "Improve list girl group customer likely. Produce human certain quality star.",
        "external_references": [
            {
                "external_id": "oiynaFLrNcKYSa",
                "source_name": "compare"
            },
            {
                "description": "Customer key mention.",
                "source_name": "although"
            },
            {
                "description": "Attention to nearly rate.",
                "external_id": "LaDGt",
                "source_name": "may",
                "url": "http://turner-montgomery.com/"
            },
            {
                "external_id": "WDLgxW",
                "source_name": "television"
            }
        ],
        "id": "relationship--d250224b-04f0-4475-88a4-147cec910d27",
        "labels": [
            "theory",
            "year",
            "country",
            "her",
            "his",
            "pfte-batch-1"
        ],
        "lang": "en",
        "modified": "2022-06-29T17:52:13.056645Z",
        "object_marking_refs": [
            "marking-definition--da4f7162-ce1c-4172-9693-45efd33a5ea7"
        ],
        "relationship_type": "targets",
        "source_ref": "tool--2e506862-cee3-4f39-8719-950b7995de3c",
        "spec_version": "2.1",
        "stop_time": "2020-08-18T14:22:29.570358Z",
        "target_ref": "identity--f31d8454-3e50-412e-8d21-5d827d02cf47",
        "type": "relationship"
    },
    {
        "administrative_area": "MhhHzPKGgodfoH",
        "city": "Lake Anna",
        "confidence": 63,
        "created": "2021-05-12T17:29:28.739768Z",
        "created_by_ref": "identity--dbe5b8d1-7fe0-4bec-b5b1-8dcbeb7b2879",
        "id": "location--d646efcb-ce90-4539-8c72-66404c5e5467",
        "labels": [
            "argue",
            "commercial",
            "cause",
            "pressure",
            "our",
            "pfte-batch-1"
        ],
        "lang": "en",
        "latitude": 11.574796526992102,
        "longitude": -112.55422555810036,
        "modified": "2021-08-14T01:08:26.89491Z",
        "name": "pYdjjCBglondasHs",
        "object_marking_refs": [
            "marking-definition--da4f7162-ce1c-4172-9693-45efd33a5ea7"
        ],
        "postal_code": "93927",
        "precision": 38.82254252559774,
        "spec_version": "2.1",
        "street_address": "5383 Davis Manors Suite 497",
        "type": "location"
    },
    {
        "confidence": 75,
        "created": "2021-10-02T19:50:05.237352Z",
        "created_by_ref": "identity--dbe5b8d1-7fe0-4bec-b5b1-8dcbeb7b2879",
        "description": "Effect crime choose sense girl statement. Style item continue can moment mind school.",
        "id": "relationship--bc6f2f9d-bb86-46d3-9bab-f984d1b4d4b2",
        "modified": "2022-04-04T23:24:28.987634Z",
        "object_marking_refs": [
            "marking-definition--da4f7162-ce1c-4172-9693-45efd33a5ea7"
        ],
        "relationship_type": "located-at",
        "source_ref": "identity--f31d8454-3e50-412e-8d21-5d827d02cf47",
        "spec_version": "2.1",
        "start_time": "2020-09-02T23:10:10.703449Z",
        "target_ref": "location--d646efcb-ce90-4539-8c72-66404c5e5467",
        "type": "relationship",
        "labels": [
            "pfte-batch-1"
        ]
    }
]